alfendiwin/__init__.py
alfendiwin/sql.py
alfendiwin/taifex.py
alfendiwin/util.py
alfendiwin-0.0.2.dist-info/LICENSE
alfendiwin-0.0.2.dist-info/METADATA
alfendiwin-0.0.2.dist-info/WHEEL
alfendiwin-0.0.2.dist-info/top_level.txt
alfendiwin-0.0.2.dist-info/RECORD
