Metadata-Version: 2.1
Name: alfendiwin
Version: 0.0.2
Summary: Daily use
Home-page: UNKNOWN
Author: Lee, Wei-Chun
Author-email: ninivivian@protonmail.com
License: UNKNOWN
Platform: UNKNOWN
Classifier: Programming Language :: Python :: 3
Classifier: License :: OSI Approved :: MIT License
Classifier: Operating System :: OS Independent
Requires-Python: >=3.6
License-File: LICENSE
Requires-Dist: requests
Requires-Dist: pandas (>=1)
